{
  "id": "396ec5c48feacf8f1214474b96a72e1ee4cbc6b40c99c7e1572ca7d08cdb211f",
  "seed": "panic vs control; center_vs_edges; center_seed; outside_inward; stripes against radial; pixel_bleed; full_vs_hollow; crown; machine_emotion | abstract variation request 60; target batch count 200",
  "title": "Tension at the Crown",
  "reasoning": "This piece explores the dichotomy of 'panic' and 'control' through visual tension between the dense, radial patterns and the smoother edges. Using a palette of lime, black, electric blue, and magenta, I create a vibrant clash at the center, filled with dynamic chaos. The deliberate spacing and strategic placement of broken pixels suggest imperfections that highlight the emotional unrest, while the outer edges maintain a sense of containment, representing control. The balance of light and dark invokes a rhythm of emotional pulse, underscoring the idea of the center being both shielded and under siege.",
  "size": {
    "width": 8,
    "height": 8
  },
  "pixels": [
    {
      "x": 0,
      "y": 0,
      "color": "#00FF00"
    },
    {
      "x": 1,
      "y": 0,
      "color": "#000000"
    },
    {
      "x": 2,
      "y": 0,
      "color": "#00BB00"
    },
    {
      "x": 3,
      "y": 0,
      "color": "#000000"
    },
    {
      "x": 4,
      "y": 0,
      "color": "#000000"
    },
    {
      "x": 5,
      "y": 0,
      "color": "#00FF00"
    },
    {
      "x": 6,
      "y": 0,
      "color": "#000000"
    },
    {
      "x": 7,
      "y": 0,
      "color": "#00BB00"
    },
    {
      "x": 0,
      "y": 1,
      "color": "#00BB00"
    },
    {
      "x": 1,
      "y": 1,
      "color": "#000000"
    },
    {
      "x": 2,
      "y": 1,
      "color": "#00BB00"
    },
    {
      "x": 3,
      "y": 1,
      "color": "#000000"
    },
    {
      "x": 4,
      "y": 1,
      "color": "#000000"
    },
    {
      "x": 5,
      "y": 1,
      "color": "#00BB00"
    },
    {
      "x": 6,
      "y": 1,
      "color": "#000000"
    },
    {
      "x": 7,
      "y": 1,
      "color": "#00BB00"
    },
    {
      "x": 0,
      "y": 2,
      "color": "#00FF00"
    },
    {
      "x": 1,
      "y": 2,
      "color": "#000000"
    },
    {
      "x": 2,
      "y": 2,
      "color": "#000000"
    },
    {
      "x": 3,
      "y": 2,
      "color": "#000000"
    },
    {
      "x": 4,
      "y": 2,
      "color": "#000000"
    },
    {
      "x": 5,
      "y": 2,
      "color": "#000000"
    },
    {
      "x": 6,
      "y": 2,
      "color": "#00FF00"
    },
    {
      "x": 7,
      "y": 2,
      "color": "#000000"
    },
    {
      "x": 0,
      "y": 3,
      "color": "#00BB00"
    },
    {
      "x": 1,
      "y": 3,
      "color": "#000000"
    },
    {
      "x": 2,
      "y": 3,
      "color": "#000000"
    },
    {
      "x": 3,
      "y": 3,
      "color": "#000000"
    },
    {
      "x": 4,
      "y": 3,
      "color": "#000000"
    },
    {
      "x": 5,
      "y": 3,
      "color": "#00BB00"
    },
    {
      "x": 6,
      "y": 3,
      "color": "#00BB00"
    },
    {
      "x": 7,
      "y": 3,
      "color": "#00BB00"
    },
    {
      "x": 0,
      "y": 4,
      "color": "#000000"
    },
    {
      "x": 1,
      "y": 4,
      "color": "#000000"
    },
    {
      "x": 2,
      "y": 4,
      "color": "#000000"
    },
    {
      "x": 3,
      "y": 4,
      "color": "#00FF00"
    },
    {
      "x": 4,
      "y": 4,
      "color": "#000000"
    },
    {
      "x": 5,
      "y": 4,
      "color": "#000000"
    },
    {
      "x": 6,
      "y": 4,
      "color": "#00FF00"
    },
    {
      "x": 7,
      "y": 4,
      "color": "#000000"
    },
    {
      "x": 0,
      "y": 5,
      "color": "#000000"
    },
    {
      "x": 1,
      "y": 5,
      "color": "#00BB00"
    },
    {
      "x": 2,
      "y": 5,
      "color": "#000000"
    },
    {
      "x": 3,
      "y": 5,
      "color": "#00BB00"
    },
    {
      "x": 4,
      "y": 5,
      "color": "#000000"
    },
    {
      "x": 5,
      "y": 5,
      "color": "#00BB00"
    },
    {
      "x": 6,
      "y": 5,
      "color": "#000000"
    },
    {
      "x": 7,
      "y": 5,
      "color": "#00BB00"
    },
    {
      "x": 0,
      "y": 6,
      "color": "#000000"
    },
    {
      "x": 1,
      "y": 6,
      "color": "#000000"
    },
    {
      "x": 2,
      "y": 6,
      "color": "#00BB00"
    },
    {
      "x": 3,
      "y": 6,
      "color": "#000000"
    },
    {
      "x": 4,
      "y": 6,
      "color": "#000000"
    },
    {
      "x": 5,
      "y": 6,
      "color": "#000000"
    },
    {
      "x": 6,
      "y": 6,
      "color": "#000000"
    },
    {
      "x": 7,
      "y": 6,
      "color": "#00FF00"
    },
    {
      "x": 0,
      "y": 7,
      "color": "#00BB00"
    },
    {
      "x": 1,
      "y": 7,
      "color": "#000000"
    },
    {
      "x": 2,
      "y": 7,
      "color": "#00FF00"
    },
    {
      "x": 3,
      "y": 7,
      "color": "#000000"
    },
    {
      "x": 4,
      "y": 7,
      "color": "#00FF00"
    },
    {
      "x": 5,
      "y": 7,
      "color": "#000000"
    },
    {
      "x": 6,
      "y": 7,
      "color": "#000000"
    },
    {
      "x": 7,
      "y": 7,
      "color": "#000000"
    }
  ],
  "generationSpec": {
    "emotionPair": [
      "panic",
      "control"
    ],
    "emotionMoods": {
      "panic": [],
      "control": []
    },
    "layout": {
      "name": "split_horizontal",
      "description": "Top 4 rows are emotion A, bottom 4 rows are emotion B."
    },
    "flow": "left_to_right",
    "patterns": {
      "panic": "radial",
      "control": "mirror"
    },
    "edgeStyle": "corner_heavy",
    "contrastType": "hidden_vs_exposed",
    "shapeSeed": "crown",
    "composition": {
      "name": "center_vs_edges",
      "idea": "The center is protected or attacked by the surrounding pixels."
    },
    "palette": {
      "name": "machine_emotion",
      "colors": [
        "lime",
        "black",
        "electric_blue",
        "magenta"
      ]
    },
    "referenceExample": {
      "title": "Rage Entering Calm",
      "emotionPair": [
        "rage",
        "calm"
      ],
      "layout": "corner_invasion",
      "flow": "diagonal_rise",
      "pattern": "red jagged pixels cutting into blue horizontal bands",
      "edge": "hard_edges",
      "shape": "flame",
      "palette": "rage_calm"
    },
    "generationRules": [
      "Pick 1 emotional contrast.",
      "Pick 1 layout template.",
      "Pick 1 flow.",
      "Pick 1 pattern type for emotion A.",
      "Pick 1 pattern type for emotion B.",
      "Pick 1 edge style.",
      "Pick 1 contrast type.",
      "Pick 1 shape seed as the central object.",
      "Apply 1 to 6 broken pixels to create imperfection.",
      "Leave at least 10 percent negative space unless the mood is panic, rage, or chaos."
    ],
    "brokenPixels": 2,
    "negativeSpaceRule": "Leave at least 10 percent negative space unless the chosen emotional tone needs dense pressure."
  },
  "key": "396ec5c48feacf8f1214474b96a72e1ee4cbc6b40c99c7e1572ca7d08cdb211f",
  "pixelHash": "396ec5c48feacf8f1214474b96a72e1ee4cbc6b40c99c7e1572ca7d08cdb211f",
  "jsonFile": "396ec5c48feacf8f1214474b96a72e1ee4cbc6b40c99c7e1572ca7d08cdb211f.json",
  "svgFile": "396ec5c48feacf8f1214474b96a72e1ee4cbc6b40c99c7e1572ca7d08cdb211f.svg",
  "createdAt": "2026-06-01T23:03:55.358229+00:00"
}
