{
  "id": "7fe93c107663d7e8b5953cfe0b8cb81abbe547567f9dfc3c822776761cbe8d31",
  "seed": "loneliness vs connection; light_vs_weight; corner_invasion; right_to_left; flame against broken_dots; left_weighted; full_vs_hollow; single_pixel; broken_memory | abstract variation request 85; target batch count 200",
  "title": "Connections in Shadows",
  "reasoning": "The emotional tone reflects a struggle between feelings of loneliness and connection, juxtaposed against the idea of lightness and weight. The chosen palette of dark maroon, gray, pink, and red highlights tension, with dark shades representing loneliness pressing against the brighter tones of connection. The layout climbs upward, creating a sense of hope alternated with bursts of energy emerging from the depths. Boundaries are delineated using burned edges to signify the imperfections of memories and emotions. The collision between muted darks and vibrant highlights underscores a constant push and pull, inviting viewers to contemplate the complexity of their own emotional landscapes.",
  "size": {
    "width": 8,
    "height": 8
  },
  "pixels": [
    {
      "x": 0,
      "y": 0,
      "color": "#4B0921"
    },
    {
      "x": 1,
      "y": 0,
      "color": "#7C4C63"
    },
    {
      "x": 2,
      "y": 0,
      "color": "#BA4A36"
    },
    {
      "x": 3,
      "y": 0,
      "color": "#F2B2C3"
    },
    {
      "x": 4,
      "y": 0,
      "color": "#FFF2F2"
    },
    {
      "x": 5,
      "y": 0,
      "color": "#BA4A36"
    },
    {
      "x": 6,
      "y": 0,
      "color": "#4B0921"
    },
    {
      "x": 7,
      "y": 0,
      "color": "#3A0A1E"
    },
    {
      "x": 0,
      "y": 1,
      "color": "#6B7DA2"
    },
    {
      "x": 1,
      "y": 1,
      "color": "#5C5F7A"
    },
    {
      "x": 2,
      "y": 1,
      "color": "#BA4A36"
    },
    {
      "x": 3,
      "y": 1,
      "color": "#FFF2F2"
    },
    {
      "x": 4,
      "y": 1,
      "color": "#F2B2C3"
    },
    {
      "x": 5,
      "y": 1,
      "color": "#BA4A36"
    },
    {
      "x": 6,
      "y": 1,
      "color": "#3A0A1E"
    },
    {
      "x": 7,
      "y": 1,
      "color": "#BF6A92"
    },
    {
      "x": 0,
      "y": 2,
      "color": "#BA4A36"
    },
    {
      "x": 1,
      "y": 2,
      "color": "#F2B2C3"
    },
    {
      "x": 2,
      "y": 2,
      "color": "#7C4C63"
    },
    {
      "x": 3,
      "y": 2,
      "color": "#3A0A1E"
    },
    {
      "x": 4,
      "y": 2,
      "color": "#4B0921"
    },
    {
      "x": 5,
      "y": 2,
      "color": "#6B7DA2"
    },
    {
      "x": 6,
      "y": 2,
      "color": "#6B6F81"
    },
    {
      "x": 7,
      "y": 2,
      "color": "#D1C163"
    },
    {
      "x": 0,
      "y": 3,
      "color": "#000000"
    },
    {
      "x": 1,
      "y": 3,
      "color": "#4B0921"
    },
    {
      "x": 2,
      "y": 3,
      "color": "#7C4C63"
    },
    {
      "x": 3,
      "y": 3,
      "color": "#F2B2C3"
    },
    {
      "x": 4,
      "y": 3,
      "color": "#6B7DA2"
    },
    {
      "x": 5,
      "y": 3,
      "color": "#BA4A36"
    },
    {
      "x": 6,
      "y": 3,
      "color": "#D1C163"
    },
    {
      "x": 7,
      "y": 3,
      "color": "#BF6A92"
    },
    {
      "x": 0,
      "y": 4,
      "color": "#3A0A1E"
    },
    {
      "x": 1,
      "y": 4,
      "color": "#3A0A1E"
    },
    {
      "x": 2,
      "y": 4,
      "color": "#BA4A36"
    },
    {
      "x": 3,
      "y": 4,
      "color": "#F2B2C3"
    },
    {
      "x": 4,
      "y": 4,
      "color": "#FFF2F2"
    },
    {
      "x": 5,
      "y": 4,
      "color": "#D1B89F"
    },
    {
      "x": 6,
      "y": 4,
      "color": "#7C4C63"
    },
    {
      "x": 7,
      "y": 4,
      "color": "#4B0921"
    },
    {
      "x": 0,
      "y": 5,
      "color": "#BF6A92"
    },
    {
      "x": 1,
      "y": 5,
      "color": "#000000"
    },
    {
      "x": 2,
      "y": 5,
      "color": "#FFFFFF"
    },
    {
      "x": 3,
      "y": 5,
      "color": "#D1C163"
    },
    {
      "x": 4,
      "y": 5,
      "color": "#6B7DA2"
    },
    {
      "x": 5,
      "y": 5,
      "color": "#BA4A36"
    },
    {
      "x": 6,
      "y": 5,
      "color": "#4B0921"
    },
    {
      "x": 7,
      "y": 5,
      "color": "#4B0921"
    },
    {
      "x": 0,
      "y": 6,
      "color": "#7C4C63"
    },
    {
      "x": 1,
      "y": 6,
      "color": "#D1C163"
    },
    {
      "x": 2,
      "y": 6,
      "color": "#F2B2C3"
    },
    {
      "x": 3,
      "y": 6,
      "color": "#BA4A36"
    },
    {
      "x": 4,
      "y": 6,
      "color": "#BF6A92"
    },
    {
      "x": 5,
      "y": 6,
      "color": "#D1C163"
    },
    {
      "x": 6,
      "y": 6,
      "color": "#FFFFFF"
    },
    {
      "x": 7,
      "y": 6,
      "color": "#BF6A92"
    },
    {
      "x": 0,
      "y": 7,
      "color": "#000000"
    },
    {
      "x": 1,
      "y": 7,
      "color": "#BF6A92"
    },
    {
      "x": 2,
      "y": 7,
      "color": "#3A0A1E"
    },
    {
      "x": 3,
      "y": 7,
      "color": "#D1B89F"
    },
    {
      "x": 4,
      "y": 7,
      "color": "#6B7DA2"
    },
    {
      "x": 5,
      "y": 7,
      "color": "#F2B2C3"
    },
    {
      "x": 6,
      "y": 7,
      "color": "#BA4A36"
    },
    {
      "x": 7,
      "y": 7,
      "color": "#3A0A1E"
    }
  ],
  "generationSpec": {
    "emotionPair": [
      "loneliness",
      "connection"
    ],
    "emotionMoods": {
      "loneliness": [
        "large negative space",
        "off-center",
        "single dot"
      ],
      "connection": []
    },
    "layout": {
      "name": "rising_signal",
      "description": "Pixels climb upward from bottom to top like hope or escape."
    },
    "flow": "scatter",
    "patterns": {
      "loneliness": "noise",
      "connection": "checker"
    },
    "edgeStyle": "burned_edges",
    "contrastType": "warm_vs_cool",
    "shapeSeed": "stair_step",
    "composition": {
      "name": "inside_vs_outside",
      "idea": "A small inner shape is surrounded by pressure, noise, or protection."
    },
    "palette": {
      "name": "love_betrayal",
      "colors": [
        "pink",
        "red",
        "gray",
        "dark_maroon"
      ]
    },
    "referenceExample": {
      "title": "Lonely Signal",
      "emotionPair": [
        "loneliness",
        "connection"
      ],
      "layout": "empty_room",
      "flow": "pulse",
      "pattern": "single bright dot with faint surrounding echo",
      "edge": "soft_edges",
      "shape": "single_pixel",
      "palette": "lonely_signal"
    },
    "generationRules": [
      "Pick 1 emotional contrast.",
      "Pick 1 layout template.",
      "Pick 1 flow.",
      "Pick 1 pattern type for emotion A.",
      "Pick 1 pattern type for emotion B.",
      "Pick 1 edge style.",
      "Pick 1 contrast type.",
      "Pick 1 shape seed as the central object.",
      "Apply 1 to 6 broken pixels to create imperfection.",
      "Leave at least 10 percent negative space unless the mood is panic, rage, or chaos."
    ],
    "brokenPixels": 5,
    "negativeSpaceRule": "Leave at least 10 percent negative space unless the chosen emotional tone needs dense pressure."
  },
  "key": "7fe93c107663d7e8b5953cfe0b8cb81abbe547567f9dfc3c822776761cbe8d31",
  "pixelHash": "7fe93c107663d7e8b5953cfe0b8cb81abbe547567f9dfc3c822776761cbe8d31",
  "jsonFile": "7fe93c107663d7e8b5953cfe0b8cb81abbe547567f9dfc3c822776761cbe8d31.json",
  "svgFile": "7fe93c107663d7e8b5953cfe0b8cb81abbe547567f9dfc3c822776761cbe8d31.svg",
  "createdAt": "2026-06-02T05:17:53.140398+00:00"
}
