{
  "id": "92b871e0761256af3466a6ce9a7164a6bf792673e3ef52ad79f1cfb8a597390a",
  "seed": "emptiness vs desire; overflow_vs_containment; rising_signal; spiral_counterclockwise; teeth against frame; cut_edges; ordered_vs_disrupted; corner_block; quiet_pressure | abstract variation request 471; target batch count 500",
  "title": "Hunger vs. Restraint",
  "reasoning": "This artwork captures the emotional tension between desire and emptiness. The chosen palette of hot coral, blood orange, and dust pink represents the intense pull of desire, contrasted by the hollow blue and charcoal representing the emptiness. The collision occurs at the center where the warm saturated colors sharply interact with the cooler, muted tones, creating an area of visual tension that embodies 'hunger vs. restraint'. The layout of the piece is intentionally divided to reflect the struggle between overflowing desire and the containment of emptiness, allowing for a narrative of dynamic conflict and resolution through color placement.",
  "size": {
    "width": 8,
    "height": 8
  },
  "pixels": [
    {
      "x": 0,
      "y": 0,
      "color": "#FF6F61"
    },
    {
      "x": 1,
      "y": 0,
      "color": "#FF4F27"
    },
    {
      "x": 2,
      "y": 0,
      "color": "#FFABAB"
    },
    {
      "x": 3,
      "y": 0,
      "color": "#B0B3D2"
    },
    {
      "x": 4,
      "y": 0,
      "color": "#4B4E6D"
    },
    {
      "x": 5,
      "y": 0,
      "color": "#B0B3D2"
    },
    {
      "x": 6,
      "y": 0,
      "color": "#FFABAB"
    },
    {
      "x": 7,
      "y": 0,
      "color": "#FF4F27"
    },
    {
      "x": 0,
      "y": 1,
      "color": "#FF7F50"
    },
    {
      "x": 1,
      "y": 1,
      "color": "#FF4500"
    },
    {
      "x": 2,
      "y": 1,
      "color": "#F5C7B2"
    },
    {
      "x": 3,
      "y": 1,
      "color": "#D2D6E1"
    },
    {
      "x": 4,
      "y": 1,
      "color": "#4E545D"
    },
    {
      "x": 5,
      "y": 1,
      "color": "#D2D6E1"
    },
    {
      "x": 6,
      "y": 1,
      "color": "#F5C7B2"
    },
    {
      "x": 7,
      "y": 1,
      "color": "#FF4500"
    },
    {
      "x": 0,
      "y": 2,
      "color": "#FF6347"
    },
    {
      "x": 1,
      "y": 2,
      "color": "#FF4500"
    },
    {
      "x": 2,
      "y": 2,
      "color": "#E2D4D4"
    },
    {
      "x": 3,
      "y": 2,
      "color": "#A7AEB7"
    },
    {
      "x": 4,
      "y": 2,
      "color": "#6D737C"
    },
    {
      "x": 5,
      "y": 2,
      "color": "#A7AEB7"
    },
    {
      "x": 6,
      "y": 2,
      "color": "#E2D4D4"
    },
    {
      "x": 7,
      "y": 2,
      "color": "#FF4500"
    },
    {
      "x": 0,
      "y": 3,
      "color": "#FF4F27"
    },
    {
      "x": 1,
      "y": 3,
      "color": "#FF6F61"
    },
    {
      "x": 2,
      "y": 3,
      "color": "#EAE4EA"
    },
    {
      "x": 3,
      "y": 3,
      "color": "#F2F2F2"
    },
    {
      "x": 4,
      "y": 3,
      "color": "#6D737C"
    },
    {
      "x": 5,
      "y": 3,
      "color": "#F2F2F2"
    },
    {
      "x": 6,
      "y": 3,
      "color": "#EAE4EA"
    },
    {
      "x": 7,
      "y": 3,
      "color": "#FF6F61"
    },
    {
      "x": 0,
      "y": 4,
      "color": "#FF8C5A"
    },
    {
      "x": 1,
      "y": 4,
      "color": "#FF7043"
    },
    {
      "x": 2,
      "y": 4,
      "color": "#E3C6A3"
    },
    {
      "x": 3,
      "y": 4,
      "color": "#C6D4E8"
    },
    {
      "x": 4,
      "y": 4,
      "color": "#3C3F43"
    },
    {
      "x": 5,
      "y": 4,
      "color": "#C6D4E8"
    },
    {
      "x": 6,
      "y": 4,
      "color": "#E3C6A3"
    },
    {
      "x": 7,
      "y": 4,
      "color": "#FF7043"
    },
    {
      "x": 0,
      "y": 5,
      "color": "#FFB6A4"
    },
    {
      "x": 1,
      "y": 5,
      "color": "#FF8C5A"
    },
    {
      "x": 2,
      "y": 5,
      "color": "#C0B3C6"
    },
    {
      "x": 3,
      "y": 5,
      "color": "#B9C0D6"
    },
    {
      "x": 4,
      "y": 5,
      "color": "#3D4043"
    },
    {
      "x": 5,
      "y": 5,
      "color": "#B9C0D6"
    },
    {
      "x": 6,
      "y": 5,
      "color": "#C0B3C6"
    },
    {
      "x": 7,
      "y": 5,
      "color": "#FF8C5A"
    },
    {
      "x": 0,
      "y": 6,
      "color": "#D3C9D7"
    },
    {
      "x": 1,
      "y": 6,
      "color": "#FFC3B4"
    },
    {
      "x": 2,
      "y": 6,
      "color": "#C2B8D4"
    },
    {
      "x": 3,
      "y": 6,
      "color": "#A3A8B0"
    },
    {
      "x": 4,
      "y": 6,
      "color": "#2A2D30"
    },
    {
      "x": 5,
      "y": 6,
      "color": "#A3A8B0"
    },
    {
      "x": 6,
      "y": 6,
      "color": "#C2B8D4"
    },
    {
      "x": 7,
      "y": 6,
      "color": "#FFC3B4"
    },
    {
      "x": 0,
      "y": 7,
      "color": "#F8F9FA"
    },
    {
      "x": 1,
      "y": 7,
      "color": "#E2C985"
    },
    {
      "x": 2,
      "y": 7,
      "color": "#D1B1D1"
    },
    {
      "x": 3,
      "y": 7,
      "color": "#A19BB0"
    },
    {
      "x": 4,
      "y": 7,
      "color": "#1D2125"
    },
    {
      "x": 5,
      "y": 7,
      "color": "#A19BB0"
    },
    {
      "x": 6,
      "y": 7,
      "color": "#D1B1D1"
    },
    {
      "x": 7,
      "y": 7,
      "color": "#E2C985"
    }
  ],
  "generationSpec": {
    "emotionPair": [
      "emptiness",
      "desire"
    ],
    "emotionMoods": {
      "emptiness": [
        "faint perimeter",
        "low saturation",
        "large blank area"
      ],
      "desire": [
        "saturated pulse",
        "gathered glow",
        "warm pull"
      ]
    },
    "layout": {
      "name": "threshold",
      "description": "The canvas is divided by a passage or seam where the two emotions meet."
    },
    "flow": "diagonal_rise",
    "patterns": {
      "emptiness": "glitch",
      "desire": "shatter"
    },
    "edgeStyle": "receding_edges",
    "contrastType": "rising_vs_falling",
    "shapeSeed": "flame",
    "composition": {
      "name": "hunger_vs_restraint",
      "idea": "A saturated pull reaches toward a locked border that refuses expansion."
    },
    "palette": {
      "name": "desire_emptiness",
      "colors": [
        "hot_coral",
        "blood_orange",
        "dust_pink",
        "charcoal",
        "hollow_blue"
      ]
    },
    "referenceExample": {
      "title": "Desire Held Back",
      "emotionPair": [
        "desire",
        "restraint"
      ],
      "layout": "threshold",
      "flow": "advance",
      "pattern": "warm saturated pull stopped by a cool sealed boundary",
      "edge": "sealed_edges",
      "shape": "wall",
      "palette": "desire_emptiness"
    },
    "generationRules": [
      "Pick 1 emotional contrast.",
      "Pick 1 layout template.",
      "Pick 1 flow.",
      "Pick 1 pattern type for emotion A.",
      "Pick 1 pattern type for emotion B.",
      "Pick 1 edge style.",
      "Pick 1 contrast type.",
      "Pick 1 shape seed as the central object.",
      "Apply 1 to 6 broken pixels to create imperfection.",
      "Leave at least 10 percent negative space unless the mood is panic, rage, urgency, euphoria, or pressure.",
      "Use the shape seed as an abstract organizing metaphor, not as a literal icon.",
      "Make the two selected pattern types visibly collide, overlap, interrupt, or trade space.",
      "Prefer 4 to 8 distinct hex colors, with at least one quiet field color and one accent color.",
      "Keep the 8x8 grid readable at thumbnail size by preserving clear large-scale structure.",
      "Let one emotion dominate 55 to 70 percent of the square unless the selected layout demands balance.",
      "Use broken pixels as intentional disruptions, scars, repairs, leaks, or false echoes.",
      "Avoid perfectly even distribution unless the chosen composition is control, serenity, clarity, or certainty.",
      "Give the main collision a location: center, edge, corner, diagonal, border, or channel."
    ],
    "brokenPixels": 2,
    "negativeSpaceRule": "Leave at least 10 percent negative space unless the chosen emotional tone needs dense pressure."
  },
  "key": "92b871e0761256af3466a6ce9a7164a6bf792673e3ef52ad79f1cfb8a597390a",
  "pixelHash": "92b871e0761256af3466a6ce9a7164a6bf792673e3ef52ad79f1cfb8a597390a",
  "jsonFile": "92b871e0761256af3466a6ce9a7164a6bf792673e3ef52ad79f1cfb8a597390a.json",
  "svgFile": "92b871e0761256af3466a6ce9a7164a6bf792673e3ef52ad79f1cfb8a597390a.svg",
  "createdAt": "2026-06-07T22:24:22.797980+00:00"
}
