{
  "id": "9e5f8c208a3909e059a47410e907e69711bd6d60f58753533589dde3d4ab0a3e",
  "seed": "loneliness vs connection; inside_vs_outside; center_seed; burst; crosshatch against grid; top_weighted; hidden_vs_exposed; tear; ancient_fire | abstract variation request 47; target batch count 200",
  "title": "Echoes of Connection",
  "reasoning": "The artwork captures the emotional contrasts of loneliness and connection through an interplay of deep contrasts and layered textures. The palette of burnt orange, dark red, charcoal, and gold reflects ancient fire, evoking warmth amidst solitude. The main collision occurs where deep tones meet, echoing the hidden pain of disconnection and the distant possibility of connection at the center\u2014a single burst of brightness representing fleeting moments of warmth. The grid pattern speaks to the structural boundaries of loneliness while allowing for a subtle noise of connection to weave through, establishing a narrative of tension and potential.",
  "size": {
    "width": 8,
    "height": 8
  },
  "pixels": [
    {
      "x": 0,
      "y": 0,
      "color": "#3B5C2C"
    },
    {
      "x": 1,
      "y": 0,
      "color": "#302D1E"
    },
    {
      "x": 2,
      "y": 0,
      "color": "#7C2A13"
    },
    {
      "x": 3,
      "y": 0,
      "color": "#4F3B2D"
    },
    {
      "x": 4,
      "y": 0,
      "color": "#B34715"
    },
    {
      "x": 5,
      "y": 0,
      "color": "#D55D2B"
    },
    {
      "x": 6,
      "y": 0,
      "color": "#FFF5E1"
    },
    {
      "x": 7,
      "y": 0,
      "color": "#BEC0C6"
    },
    {
      "x": 0,
      "y": 1,
      "color": "#6B3F35"
    },
    {
      "x": 1,
      "y": 1,
      "color": "#653F2B"
    },
    {
      "x": 2,
      "y": 1,
      "color": "#B37855"
    },
    {
      "x": 3,
      "y": 1,
      "color": "#DDAF84"
    },
    {
      "x": 4,
      "y": 1,
      "color": "#7A4B39"
    },
    {
      "x": 5,
      "y": 1,
      "color": "#453A2D"
    },
    {
      "x": 6,
      "y": 1,
      "color": "#FBDBA0"
    },
    {
      "x": 7,
      "y": 1,
      "color": "#7385A2"
    },
    {
      "x": 0,
      "y": 2,
      "color": "#597F83"
    },
    {
      "x": 1,
      "y": 2,
      "color": "#B88A67"
    },
    {
      "x": 2,
      "y": 2,
      "color": "#4B3218"
    },
    {
      "x": 3,
      "y": 2,
      "color": "#8A5B3F"
    },
    {
      "x": 4,
      "y": 2,
      "color": "#A45E2D"
    },
    {
      "x": 5,
      "y": 2,
      "color": "#6B1D11"
    },
    {
      "x": 6,
      "y": 2,
      "color": "#E8B82D"
    },
    {
      "x": 7,
      "y": 2,
      "color": "#B59DA0"
    },
    {
      "x": 0,
      "y": 3,
      "color": "#784529"
    },
    {
      "x": 1,
      "y": 3,
      "color": "#EBA273"
    },
    {
      "x": 2,
      "y": 3,
      "color": "#48403A"
    },
    {
      "x": 3,
      "y": 3,
      "color": "#D68639"
    },
    {
      "x": 4,
      "y": 3,
      "color": "#A35324"
    },
    {
      "x": 5,
      "y": 3,
      "color": "#6E3F24"
    },
    {
      "x": 6,
      "y": 3,
      "color": "#4D4B4D"
    },
    {
      "x": 7,
      "y": 3,
      "color": "#D0D3D4"
    },
    {
      "x": 0,
      "y": 4,
      "color": "#5C3833"
    },
    {
      "x": 1,
      "y": 4,
      "color": "#7C4331"
    },
    {
      "x": 2,
      "y": 4,
      "color": "#D2AB4D"
    },
    {
      "x": 3,
      "y": 4,
      "color": "#8C6F56"
    },
    {
      "x": 4,
      "y": 4,
      "color": "#CF7549"
    },
    {
      "x": 5,
      "y": 4,
      "color": "#935042"
    },
    {
      "x": 6,
      "y": 4,
      "color": "#BCB6A4"
    },
    {
      "x": 7,
      "y": 4,
      "color": "#1F252C"
    },
    {
      "x": 0,
      "y": 5,
      "color": "#5D334D"
    },
    {
      "x": 1,
      "y": 5,
      "color": "#BF4E38"
    },
    {
      "x": 2,
      "y": 5,
      "color": "#E0B9A0"
    },
    {
      "x": 3,
      "y": 5,
      "color": "#AA6D58"
    },
    {
      "x": 4,
      "y": 5,
      "color": "#5B3F26"
    },
    {
      "x": 5,
      "y": 5,
      "color": "#1A1519"
    },
    {
      "x": 6,
      "y": 5,
      "color": "#666B70"
    },
    {
      "x": 7,
      "y": 5,
      "color": "#D88322"
    },
    {
      "x": 0,
      "y": 6,
      "color": "#7A8C7A"
    },
    {
      "x": 1,
      "y": 6,
      "color": "#E3BFFF"
    },
    {
      "x": 2,
      "y": 6,
      "color": "#42241C"
    },
    {
      "x": 3,
      "y": 6,
      "color": "#A87E39"
    },
    {
      "x": 4,
      "y": 6,
      "color": "#B35833"
    },
    {
      "x": 5,
      "y": 6,
      "color": "#3A2928"
    },
    {
      "x": 6,
      "y": 6,
      "color": "#581A0C"
    },
    {
      "x": 7,
      "y": 6,
      "color": "#F5C99E"
    },
    {
      "x": 0,
      "y": 7,
      "color": "#7D471C"
    },
    {
      "x": 1,
      "y": 7,
      "color": "#B45918"
    },
    {
      "x": 2,
      "y": 7,
      "color": "#E7C8AF"
    },
    {
      "x": 3,
      "y": 7,
      "color": "#A54A2A"
    },
    {
      "x": 4,
      "y": 7,
      "color": "#C56E29"
    },
    {
      "x": 5,
      "y": 7,
      "color": "#D0ECC4"
    },
    {
      "x": 6,
      "y": 7,
      "color": "#702A1E"
    },
    {
      "x": 7,
      "y": 7,
      "color": "#4A474D"
    }
  ],
  "generationSpec": {
    "emotionPair": [
      "loneliness",
      "connection"
    ],
    "emotionMoods": {
      "loneliness": [
        "single dot",
        "large negative space",
        "off-center"
      ],
      "connection": []
    },
    "layout": {
      "name": "empty_room",
      "description": "Mostly empty space with one meaningful object off-center."
    },
    "flow": "diagonal_rise",
    "patterns": {
      "loneliness": "grid",
      "connection": "noise"
    },
    "edgeStyle": "center_heavy",
    "contrastType": "safe_vs_threatened",
    "shapeSeed": "square_frame",
    "composition": {
      "name": "inside_vs_outside",
      "idea": "A small inner shape is surrounded by pressure, noise, or protection."
    },
    "palette": {
      "name": "ancient_fire",
      "colors": [
        "burnt_orange",
        "dark_red",
        "charcoal",
        "gold"
      ]
    },
    "referenceExample": {
      "title": "Lonely Signal",
      "emotionPair": [
        "loneliness",
        "connection"
      ],
      "layout": "empty_room",
      "flow": "pulse",
      "pattern": "single bright dot with faint surrounding echo",
      "edge": "soft_edges",
      "shape": "single_pixel",
      "palette": "lonely_signal"
    },
    "generationRules": [
      "Pick 1 emotional contrast.",
      "Pick 1 layout template.",
      "Pick 1 flow.",
      "Pick 1 pattern type for emotion A.",
      "Pick 1 pattern type for emotion B.",
      "Pick 1 edge style.",
      "Pick 1 contrast type.",
      "Pick 1 shape seed as the central object.",
      "Apply 1 to 6 broken pixels to create imperfection.",
      "Leave at least 10 percent negative space unless the mood is panic, rage, or chaos."
    ],
    "brokenPixels": 1,
    "negativeSpaceRule": "Leave at least 10 percent negative space unless the chosen emotional tone needs dense pressure."
  },
  "key": "9e5f8c208a3909e059a47410e907e69711bd6d60f58753533589dde3d4ab0a3e",
  "pixelHash": "9e5f8c208a3909e059a47410e907e69711bd6d60f58753533589dde3d4ab0a3e",
  "jsonFile": "9e5f8c208a3909e059a47410e907e69711bd6d60f58753533589dde3d4ab0a3e.json",
  "svgFile": "9e5f8c208a3909e059a47410e907e69711bd6d60f58753533589dde3d4ab0a3e.svg",
  "createdAt": "2026-06-01T20:53:17.468459+00:00"
}
