{
  "id": "a77b37a1d7eba91c3cdff792cf447e6b575f1fb61b6a217eaa11366457d37e20",
  "seed": "confusion vs clarity; symmetry_vs_break; falling_pixels; pulse; crosshatch against noise; thick_outline; symmetrical_vs_broken; tiny_face; rage_calm | abstract variation request 194; target batch count 200",
  "title": "Symmetry in Chaos",
  "reasoning": "The emotional tone of this piece captures the tension between confusion and clarity, represented by a stark contrast between dark and light. The selected palette of black, dark violet, soft gold, and pale green emphasizes this emotional juxtaposition, with the black and dark violet suggesting depth and confusion, while the soft gold and pale green signify moments of clarity. The layout is divided horizontally, with the top half representing clarity through a structured arrangement of bright colors that pulse in rhythm, while the bottom half conveys confusion with an irregular pattern of broken pixels and muted colors. This interplay creates a dynamic tension, evoking feelings of asymmetry and unresolved emotions, truly embodying the \u2018symmetry vs break\u2019 theme via its abstract composition.",
  "size": {
    "width": 8,
    "height": 8
  },
  "pixels": [
    {
      "x": 0,
      "y": 0,
      "color": "#000000"
    },
    {
      "x": 1,
      "y": 0,
      "color": "#2D2A6D"
    },
    {
      "x": 2,
      "y": 0,
      "color": "#5B5A9C"
    },
    {
      "x": 3,
      "y": 0,
      "color": "#A79B5A"
    },
    {
      "x": 4,
      "y": 0,
      "color": "#E8D5A9"
    },
    {
      "x": 5,
      "y": 0,
      "color": "#E6C15A"
    },
    {
      "x": 6,
      "y": 0,
      "color": "#FFFFBF"
    },
    {
      "x": 7,
      "y": 0,
      "color": "#FFD700"
    },
    {
      "x": 0,
      "y": 1,
      "color": "#000000"
    },
    {
      "x": 1,
      "y": 1,
      "color": "#2B2B4D"
    },
    {
      "x": 2,
      "y": 1,
      "color": "#C89B74"
    },
    {
      "x": 3,
      "y": 1,
      "color": "#BDA93D"
    },
    {
      "x": 4,
      "y": 1,
      "color": "#F1C5B7"
    },
    {
      "x": 5,
      "y": 1,
      "color": "#D3C7B0"
    },
    {
      "x": 6,
      "y": 1,
      "color": "#989B7D"
    },
    {
      "x": 7,
      "y": 1,
      "color": "#FFFFFF"
    },
    {
      "x": 0,
      "y": 2,
      "color": "#000000"
    },
    {
      "x": 1,
      "y": 2,
      "color": "#1A1A42"
    },
    {
      "x": 2,
      "y": 2,
      "color": "#B29D77"
    },
    {
      "x": 3,
      "y": 2,
      "color": "#EBC98E"
    },
    {
      "x": 4,
      "y": 2,
      "color": "#F4E5B6"
    },
    {
      "x": 5,
      "y": 2,
      "color": "#FFDC6A"
    },
    {
      "x": 6,
      "y": 2,
      "color": "#B7C100"
    },
    {
      "x": 7,
      "y": 2,
      "color": "#E5CCAA"
    },
    {
      "x": 0,
      "y": 3,
      "color": "#1E1E2E"
    },
    {
      "x": 1,
      "y": 3,
      "color": "#4A4A9D"
    },
    {
      "x": 2,
      "y": 3,
      "color": "#94B06D"
    },
    {
      "x": 3,
      "y": 3,
      "color": "#D3D99A"
    },
    {
      "x": 4,
      "y": 3,
      "color": "#E4D5C3"
    },
    {
      "x": 5,
      "y": 3,
      "color": "#E1C1AA"
    },
    {
      "x": 6,
      "y": 3,
      "color": "#DFAF79"
    },
    {
      "x": 7,
      "y": 3,
      "color": "#F5FBAF"
    },
    {
      "x": 0,
      "y": 4,
      "color": "#1A1A1A"
    },
    {
      "x": 1,
      "y": 4,
      "color": "#5A4C7D"
    },
    {
      "x": 2,
      "y": 4,
      "color": "#A3723A"
    },
    {
      "x": 3,
      "y": 4,
      "color": "#B1B2A4"
    },
    {
      "x": 4,
      "y": 4,
      "color": "#DAE6C3"
    },
    {
      "x": 5,
      "y": 4,
      "color": "#A5A39D"
    },
    {
      "x": 6,
      "y": 4,
      "color": "#8C9D5D"
    },
    {
      "x": 7,
      "y": 4,
      "color": "#E2E2E2"
    },
    {
      "x": 0,
      "y": 5,
      "color": "#000000"
    },
    {
      "x": 1,
      "y": 5,
      "color": "#3A3742"
    },
    {
      "x": 2,
      "y": 5,
      "color": "#6D5B4A"
    },
    {
      "x": 3,
      "y": 5,
      "color": "#9D7D5A"
    },
    {
      "x": 4,
      "y": 5,
      "color": "#F6E3D5"
    },
    {
      "x": 5,
      "y": 5,
      "color": "#C4C1B3"
    },
    {
      "x": 6,
      "y": 5,
      "color": "#BFBF9D"
    },
    {
      "x": 7,
      "y": 5,
      "color": "#CCBCBB"
    },
    {
      "x": 0,
      "y": 6,
      "color": "#000000"
    },
    {
      "x": 1,
      "y": 6,
      "color": "#37324A"
    },
    {
      "x": 2,
      "y": 6,
      "color": "#A54C72"
    },
    {
      "x": 3,
      "y": 6,
      "color": "#E0C6A0"
    },
    {
      "x": 4,
      "y": 6,
      "color": "#F6F2D5"
    },
    {
      "x": 5,
      "y": 6,
      "color": "#B7D8B1"
    },
    {
      "x": 6,
      "y": 6,
      "color": "#DFE4C4"
    },
    {
      "x": 7,
      "y": 6,
      "color": "#FFFFFC"
    },
    {
      "x": 0,
      "y": 7,
      "color": "#1D1D1D"
    },
    {
      "x": 1,
      "y": 7,
      "color": "#262D67"
    },
    {
      "x": 2,
      "y": 7,
      "color": "#5B5297"
    },
    {
      "x": 3,
      "y": 7,
      "color": "#A7A64A"
    },
    {
      "x": 4,
      "y": 7,
      "color": "#F6D35D"
    },
    {
      "x": 5,
      "y": 7,
      "color": "#E1D2D7"
    },
    {
      "x": 6,
      "y": 7,
      "color": "#C4BBA1"
    },
    {
      "x": 7,
      "y": 7,
      "color": "#FFFFFF"
    }
  ],
  "generationSpec": {
    "emotionPair": [
      "confusion",
      "clarity"
    ],
    "emotionMoods": {
      "confusion": [
        "false symmetry",
        "broken grid",
        "overlapping paths"
      ],
      "clarity": []
    },
    "layout": {
      "name": "split_horizontal",
      "description": "Top 4 rows are emotion A, bottom 4 rows are emotion B."
    },
    "flow": "drip",
    "patterns": {
      "confusion": "spark",
      "clarity": "spark"
    },
    "edgeStyle": "center_heavy",
    "contrastType": "hidden_vs_exposed",
    "shapeSeed": "crown",
    "composition": {
      "name": "symmetry_vs_break",
      "idea": "A nearly mirrored image has one wrong or corrupted side."
    },
    "palette": {
      "name": "fear_hope",
      "colors": [
        "black",
        "dark_violet",
        "soft_gold",
        "pale_green"
      ]
    },
    "referenceExample": {
      "title": "Lonely Signal",
      "emotionPair": [
        "loneliness",
        "connection"
      ],
      "layout": "empty_room",
      "flow": "pulse",
      "pattern": "single bright dot with faint surrounding echo",
      "edge": "soft_edges",
      "shape": "single_pixel",
      "palette": "lonely_signal"
    },
    "generationRules": [
      "Pick 1 emotional contrast.",
      "Pick 1 layout template.",
      "Pick 1 flow.",
      "Pick 1 pattern type for emotion A.",
      "Pick 1 pattern type for emotion B.",
      "Pick 1 edge style.",
      "Pick 1 contrast type.",
      "Pick 1 shape seed as the central object.",
      "Apply 1 to 6 broken pixels to create imperfection.",
      "Leave at least 10 percent negative space unless the mood is panic, rage, or chaos."
    ],
    "brokenPixels": 3,
    "negativeSpaceRule": "Leave at least 10 percent negative space unless the chosen emotional tone needs dense pressure."
  },
  "key": "a77b37a1d7eba91c3cdff792cf447e6b575f1fb61b6a217eaa11366457d37e20",
  "pixelHash": "a77b37a1d7eba91c3cdff792cf447e6b575f1fb61b6a217eaa11366457d37e20",
  "jsonFile": "a77b37a1d7eba91c3cdff792cf447e6b575f1fb61b6a217eaa11366457d37e20.json",
  "svgFile": "a77b37a1d7eba91c3cdff792cf447e6b575f1fb61b6a217eaa11366457d37e20.svg",
  "createdAt": "2026-06-01T22:00:10.359778+00:00"
}
