{
  "id": "c0989fb7874ae2713c492cf75e2dd7863b963eff6e17965fbbd1eeb82d39a681",
  "seed": "joy vs grief; symmetry_vs_break; center_seed; pulse; grid against dots; left_weighted; symmetrical_vs_broken; arrow; love_betrayal | abstract variation request 113; target batch count 200",
  "title": "Tension of Heartbeats",
  "reasoning": "The emotional tone represents the interplay between joy and grief, using a palette of warm yellow and orange for joy to contrast with the deeper blue and muted purple signifying grief. The main contrast occurs in the center where the warm tones pulse outward amidst jagged textures reflecting grief, creating a visual balance and disruption. The pattern allows for echoes of joy to clash against the structured grid of sadness, representing life\u2019s dichotomies. Broken pixels introduce imperfection, emphasizing vulnerability.",
  "size": {
    "width": 8,
    "height": 8
  },
  "pixels": [
    {
      "x": 0,
      "y": 0,
      "color": "#F7E03D"
    },
    {
      "x": 1,
      "y": 0,
      "color": "#F9A828"
    },
    {
      "x": 2,
      "y": 0,
      "color": "#D8D5F2"
    },
    {
      "x": 3,
      "y": 0,
      "color": "#5C6BA0"
    },
    {
      "x": 4,
      "y": 0,
      "color": "#4A4D95"
    },
    {
      "x": 5,
      "y": 0,
      "color": "#7A7B8D"
    },
    {
      "x": 6,
      "y": 0,
      "color": "#BFBFC4"
    },
    {
      "x": 7,
      "y": 0,
      "color": "#D1D0CE"
    },
    {
      "x": 0,
      "y": 1,
      "color": "#F7E03D"
    },
    {
      "x": 1,
      "y": 1,
      "color": "#F9A828"
    },
    {
      "x": 2,
      "y": 1,
      "color": "#D8D5F2"
    },
    {
      "x": 3,
      "y": 1,
      "color": "#5C6BA0"
    },
    {
      "x": 4,
      "y": 1,
      "color": "#4A4D95"
    },
    {
      "x": 5,
      "y": 1,
      "color": "#D1D0CE"
    },
    {
      "x": 6,
      "y": 1,
      "color": "#BFBFC4"
    },
    {
      "x": 7,
      "y": 1,
      "color": "#7A7B8D"
    },
    {
      "x": 0,
      "y": 2,
      "color": "#F9A828"
    },
    {
      "x": 1,
      "y": 2,
      "color": "#F7E03D"
    },
    {
      "x": 2,
      "y": 2,
      "color": "#5C6BA0"
    },
    {
      "x": 3,
      "y": 2,
      "color": "#D8D5F2"
    },
    {
      "x": 4,
      "y": 2,
      "color": "#4A4D95"
    },
    {
      "x": 5,
      "y": 2,
      "color": "#BFBFC4"
    },
    {
      "x": 6,
      "y": 2,
      "color": "#7A7B8D"
    },
    {
      "x": 7,
      "y": 2,
      "color": "#D1D0CE"
    },
    {
      "x": 0,
      "y": 3,
      "color": "#D8D5F2"
    },
    {
      "x": 1,
      "y": 3,
      "color": "#5C6BA0"
    },
    {
      "x": 2,
      "y": 3,
      "color": "#4A4D95"
    },
    {
      "x": 3,
      "y": 3,
      "color": "#F9A828"
    },
    {
      "x": 4,
      "y": 3,
      "color": "#F7E03D"
    },
    {
      "x": 5,
      "y": 3,
      "color": "#7A7B8D"
    },
    {
      "x": 6,
      "y": 3,
      "color": "#D1D0CE"
    },
    {
      "x": 7,
      "y": 3,
      "color": "#BFBFC4"
    },
    {
      "x": 0,
      "y": 4,
      "color": "#5C6BA0"
    },
    {
      "x": 1,
      "y": 4,
      "color": "#4A4D95"
    },
    {
      "x": 2,
      "y": 4,
      "color": "#F9A828"
    },
    {
      "x": 3,
      "y": 4,
      "color": "#F7E03D"
    },
    {
      "x": 4,
      "y": 4,
      "color": "#D8D5F2"
    },
    {
      "x": 5,
      "y": 4,
      "color": "#7A7B8D"
    },
    {
      "x": 6,
      "y": 4,
      "color": "#BFBFC4"
    },
    {
      "x": 7,
      "y": 4,
      "color": "#D1D0CE"
    },
    {
      "x": 0,
      "y": 5,
      "color": "#4A4D95"
    },
    {
      "x": 1,
      "y": 5,
      "color": "#D8D5F2"
    },
    {
      "x": 2,
      "y": 5,
      "color": "#F7E03D"
    },
    {
      "x": 3,
      "y": 5,
      "color": "#F9A828"
    },
    {
      "x": 4,
      "y": 5,
      "color": "#5C6BA0"
    },
    {
      "x": 5,
      "y": 5,
      "color": "#D1D0CE"
    },
    {
      "x": 6,
      "y": 5,
      "color": "#7A7B8D"
    },
    {
      "x": 7,
      "y": 5,
      "color": "#BFBFC4"
    },
    {
      "x": 0,
      "y": 6,
      "color": "#7A7B8D"
    },
    {
      "x": 1,
      "y": 6,
      "color": "#BFBFC4"
    },
    {
      "x": 2,
      "y": 6,
      "color": "#D1D0CE"
    },
    {
      "x": 3,
      "y": 6,
      "color": "#4A4D95"
    },
    {
      "x": 4,
      "y": 6,
      "color": "#F9A828"
    },
    {
      "x": 5,
      "y": 6,
      "color": "#F7E03D"
    },
    {
      "x": 6,
      "y": 6,
      "color": "#5C6BA0"
    },
    {
      "x": 7,
      "y": 6,
      "color": "#D8D5F2"
    },
    {
      "x": 0,
      "y": 7,
      "color": "#BFBFC4"
    },
    {
      "x": 1,
      "y": 7,
      "color": "#7A7B8D"
    },
    {
      "x": 2,
      "y": 7,
      "color": "#D1D0CE"
    },
    {
      "x": 3,
      "y": 7,
      "color": "#5C6BA0"
    },
    {
      "x": 4,
      "y": 7,
      "color": "#4A4D95"
    },
    {
      "x": 5,
      "y": 7,
      "color": "#F9A828"
    },
    {
      "x": 6,
      "y": 7,
      "color": "#F7E03D"
    },
    {
      "x": 7,
      "y": 7,
      "color": "#D8D5F2"
    }
  ],
  "generationSpec": {
    "emotionPair": [
      "joy",
      "grief"
    ],
    "emotionMoods": {
      "joy": [
        "open",
        "rounded",
        "expanding"
      ],
      "grief": [
        "blue-toned",
        "low",
        "drooping"
      ]
    },
    "layout": {
      "name": "center_seed",
      "description": "A small central symbol is surrounded by pattern pressure."
    },
    "flow": "bottom_to_top",
    "patterns": {
      "joy": "broken_dots",
      "grief": "spark"
    },
    "edgeStyle": "jagged_edges",
    "contrastType": "centered_vs_off_center",
    "shapeSeed": "wave",
    "composition": {
      "name": "center_vs_edges",
      "idea": "The center is protected or attacked by the surrounding pixels."
    },
    "palette": {
      "name": "joy_grief",
      "colors": [
        "yellow",
        "orange",
        "deep_blue",
        "muted_purple"
      ]
    },
    "referenceExample": {
      "title": "Tiny Hope Under Pressure",
      "emotionPair": [
        "fear",
        "hope"
      ],
      "layout": "center_seed",
      "flow": "outside_inward",
      "pattern": "dark frame with single bright center pixel",
      "edge": "jagged_edges",
      "shape": "seed",
      "palette": "fear_hope"
    },
    "generationRules": [
      "Pick 1 emotional contrast.",
      "Pick 1 layout template.",
      "Pick 1 flow.",
      "Pick 1 pattern type for emotion A.",
      "Pick 1 pattern type for emotion B.",
      "Pick 1 edge style.",
      "Pick 1 contrast type.",
      "Pick 1 shape seed as the central object.",
      "Apply 1 to 6 broken pixels to create imperfection.",
      "Leave at least 10 percent negative space unless the mood is panic, rage, or chaos."
    ],
    "brokenPixels": 3,
    "negativeSpaceRule": "Leave at least 10 percent negative space unless the chosen emotional tone needs dense pressure."
  },
  "key": "c0989fb7874ae2713c492cf75e2dd7863b963eff6e17965fbbd1eeb82d39a681",
  "pixelHash": "c0989fb7874ae2713c492cf75e2dd7863b963eff6e17965fbbd1eeb82d39a681",
  "jsonFile": "c0989fb7874ae2713c492cf75e2dd7863b963eff6e17965fbbd1eeb82d39a681.json",
  "svgFile": "c0989fb7874ae2713c492cf75e2dd7863b963eff6e17965fbbd1eeb82d39a681.svg",
  "createdAt": "2026-06-02T14:13:57.825835+00:00"
}
