{
  "id": "dd94ddcb94991519b0522633201ff833c4bd96fa4cb7b836b6382cbe4a6b653f",
  "seed": "relief vs dread; symmetry_vs_break; empty_room; top_to_bottom; stairs against crack; top_weighted; symmetrical_vs_broken; corner_block; rage_calm | abstract variation request 164; target batch count 200",
  "title": "Balance of Tension",
  "reasoning": "The emotional tone of this artwork captures the interplay between relief and dread, symbolizing a push and pull against chaos and calm. The palette, featuring muted sepia, tan, and dust gray tones, offers a sense of nostalgia and weight, contrasting with the faded blue that injects a feeling of lightness. This creates a visual representation of tension, where dark, heavy colors converge towards the top, suggesting the overwhelming nature of dread, while lighter hues are distributed lower, symbolizing hope and relief. The broken pixels disrupt the symmetry, embodying the fractured nature of emotions. The layout mirrors itself with intentional imperfections, representing the asymmetry of emotional balance. The flow is counterclockwise, guiding the eye across the piece while the color placements highlight the collision between peace and disturbance, drawing attention to areas of quiet space and dense clusters.",
  "size": {
    "width": 8,
    "height": 8
  },
  "pixels": [
    {
      "x": 0,
      "y": 0,
      "color": "#5C4B3A"
    },
    {
      "x": 1,
      "y": 0,
      "color": "#A68B75"
    },
    {
      "x": 2,
      "y": 0,
      "color": "#CFC1B1"
    },
    {
      "x": 3,
      "y": 0,
      "color": "#C7A67A"
    },
    {
      "x": 4,
      "y": 0,
      "color": "#7E5B49"
    },
    {
      "x": 5,
      "y": 0,
      "color": "#4B3D32"
    },
    {
      "x": 6,
      "y": 0,
      "color": "#928B76"
    },
    {
      "x": 7,
      "y": 0,
      "color": "#BEB0A4"
    },
    {
      "x": 0,
      "y": 1,
      "color": "#3B2923"
    },
    {
      "x": 1,
      "y": 1,
      "color": "#6C4E43"
    },
    {
      "x": 2,
      "y": 1,
      "color": "#D2C4B6"
    },
    {
      "x": 3,
      "y": 1,
      "color": "#E4D5C2"
    },
    {
      "x": 4,
      "y": 1,
      "color": "#A28A74"
    },
    {
      "x": 5,
      "y": 1,
      "color": "#C4B6A8"
    },
    {
      "x": 6,
      "y": 1,
      "color": "#736151"
    },
    {
      "x": 7,
      "y": 1,
      "color": "#D5D6DA"
    },
    {
      "x": 0,
      "y": 2,
      "color": "#E4E8E2"
    },
    {
      "x": 1,
      "y": 2,
      "color": "#C8C9C5"
    },
    {
      "x": 2,
      "y": 2,
      "color": "#D4D1D5"
    },
    {
      "x": 3,
      "y": 2,
      "color": "#D0C6C7"
    },
    {
      "x": 4,
      "y": 2,
      "color": "#E2E2E5"
    },
    {
      "x": 5,
      "y": 2,
      "color": "#A8A5A3"
    },
    {
      "x": 6,
      "y": 2,
      "color": "#B5A59E"
    },
    {
      "x": 7,
      "y": 2,
      "color": "#9B8B73"
    },
    {
      "x": 0,
      "y": 3,
      "color": "#7C7F7A"
    },
    {
      "x": 1,
      "y": 3,
      "color": "#7C8B8C"
    },
    {
      "x": 2,
      "y": 3,
      "color": "#576B71"
    },
    {
      "x": 3,
      "y": 3,
      "color": "#4D5550"
    },
    {
      "x": 4,
      "y": 3,
      "color": "#3A3A3A"
    },
    {
      "x": 5,
      "y": 3,
      "color": "#5F5A58"
    },
    {
      "x": 6,
      "y": 3,
      "color": "#A2A1A1"
    },
    {
      "x": 7,
      "y": 3,
      "color": "#737171"
    },
    {
      "x": 0,
      "y": 4,
      "color": "#C1B5B2"
    },
    {
      "x": 1,
      "y": 4,
      "color": "#A19B8A"
    },
    {
      "x": 2,
      "y": 4,
      "color": "#B2A5A0"
    },
    {
      "x": 3,
      "y": 4,
      "color": "#D6D1BF"
    },
    {
      "x": 4,
      "y": 4,
      "color": "#BFB4A4"
    },
    {
      "x": 5,
      "y": 4,
      "color": "#9A8D7F"
    },
    {
      "x": 6,
      "y": 4,
      "color": "#C5BFB4"
    },
    {
      "x": 7,
      "y": 4,
      "color": "#D0C6A8"
    },
    {
      "x": 0,
      "y": 5,
      "color": "#E1C5B4"
    },
    {
      "x": 1,
      "y": 5,
      "color": "#C4A08D"
    },
    {
      "x": 2,
      "y": 5,
      "color": "#B4AB95"
    },
    {
      "x": 3,
      "y": 5,
      "color": "#E2D2C7"
    },
    {
      "x": 4,
      "y": 5,
      "color": "#A9BCB0"
    },
    {
      "x": 5,
      "y": 5,
      "color": "#A0B7B8"
    },
    {
      "x": 6,
      "y": 5,
      "color": "#51545C"
    },
    {
      "x": 7,
      "y": 5,
      "color": "#2C2E2E"
    },
    {
      "x": 0,
      "y": 6,
      "color": "#D1C1B0"
    },
    {
      "x": 1,
      "y": 6,
      "color": "#A05C4B"
    },
    {
      "x": 2,
      "y": 6,
      "color": "#B09E8B"
    },
    {
      "x": 3,
      "y": 6,
      "color": "#D2E3E4"
    },
    {
      "x": 4,
      "y": 6,
      "color": "#A8C2BF"
    },
    {
      "x": 5,
      "y": 6,
      "color": "#737D7A"
    },
    {
      "x": 6,
      "y": 6,
      "color": "#A8C5C7"
    },
    {
      "x": 7,
      "y": 6,
      "color": "#D6D4CB"
    },
    {
      "x": 0,
      "y": 7,
      "color": "#E0D7C3"
    },
    {
      "x": 1,
      "y": 7,
      "color": "#D9D0B2"
    },
    {
      "x": 2,
      "y": 7,
      "color": "#CAD1B5"
    },
    {
      "x": 3,
      "y": 7,
      "color": "#515459"
    },
    {
      "x": 4,
      "y": 7,
      "color": "#808177"
    },
    {
      "x": 5,
      "y": 7,
      "color": "#536057"
    },
    {
      "x": 6,
      "y": 7,
      "color": "#D1C5C9"
    },
    {
      "x": 7,
      "y": 7,
      "color": "#D0C9BF"
    }
  ],
  "generationSpec": {
    "emotionPair": [
      "relief",
      "dread"
    ],
    "emotionMoods": {
      "relief": [],
      "dread": []
    },
    "layout": {
      "name": "mirror_broken",
      "description": "Left and right sides almost mirror, but 2 to 5 pixels are wrong."
    },
    "flow": "spiral_counterclockwise",
    "patterns": {
      "relief": "checker",
      "dread": "spark"
    },
    "edgeStyle": "left_weighted",
    "contrastType": "open_vs_closed",
    "shapeSeed": "hole",
    "composition": {
      "name": "light_vs_weight",
      "idea": "A small bright shape fights against a heavy dark mass."
    },
    "palette": {
      "name": "broken_memory",
      "colors": [
        "sepia",
        "tan",
        "dust_gray",
        "faded_blue"
      ]
    },
    "referenceExample": {
      "title": "Tiny Hope Under Pressure",
      "emotionPair": [
        "fear",
        "hope"
      ],
      "layout": "center_seed",
      "flow": "outside_inward",
      "pattern": "dark frame with single bright center pixel",
      "edge": "jagged_edges",
      "shape": "seed",
      "palette": "fear_hope"
    },
    "generationRules": [
      "Pick 1 emotional contrast.",
      "Pick 1 layout template.",
      "Pick 1 flow.",
      "Pick 1 pattern type for emotion A.",
      "Pick 1 pattern type for emotion B.",
      "Pick 1 edge style.",
      "Pick 1 contrast type.",
      "Pick 1 shape seed as the central object.",
      "Apply 1 to 6 broken pixels to create imperfection.",
      "Leave at least 10 percent negative space unless the mood is panic, rage, or chaos."
    ],
    "brokenPixels": 5,
    "negativeSpaceRule": "Leave at least 10 percent negative space unless the chosen emotional tone needs dense pressure."
  },
  "key": "dd94ddcb94991519b0522633201ff833c4bd96fa4cb7b836b6382cbe4a6b653f",
  "pixelHash": "dd94ddcb94991519b0522633201ff833c4bd96fa4cb7b836b6382cbe4a6b653f",
  "jsonFile": "dd94ddcb94991519b0522633201ff833c4bd96fa4cb7b836b6382cbe4a6b653f.json",
  "svgFile": "dd94ddcb94991519b0522633201ff833c4bd96fa4cb7b836b6382cbe4a6b653f.svg",
  "createdAt": "2026-06-02T22:08:09.678168+00:00"
}
