{
  "id": "e89229a668e1faf318cfcd2ced398ff526968b537bd0be7f02cd5f40c1b11896",
  "seed": "longing vs resolve; repair_vs_damage; mirror_broken; pulse; barcode against broken_dots; lit_edges; contained_vs_overflowing; thread; serenity_urgency | abstract variation request 396; target batch count 500",
  "title": "Tension Between States",
  "reasoning": "This abstract piece captures the emotional tension between longing and resolve through contrasting warm and cool tones. The chosen palette of warm coral and soft amber evokes a sense of longing, while the cold slate and blue-black represent resolve. The collision occurs in the center, where these contrasting patterns overlap, displaying both a flood of longing and the firm boundaries of resolve. The presence of broken pixels serves as reminders of imperfections and repairs in our emotional landscape, contributing to a narrative of struggle between completeness and incompleteness.",
  "size": {
    "width": 8,
    "height": 8
  },
  "pixels": [
    {
      "x": 0,
      "y": 0,
      "color": "#FF6F61"
    },
    {
      "x": 1,
      "y": 0,
      "color": "#FF8A5B"
    },
    {
      "x": 2,
      "y": 0,
      "color": "#F7B7A3"
    },
    {
      "x": 3,
      "y": 0,
      "color": "#F2D5C1"
    },
    {
      "x": 4,
      "y": 0,
      "color": "#A6C8E0"
    },
    {
      "x": 5,
      "y": 0,
      "color": "#4B84C6"
    },
    {
      "x": 6,
      "y": 0,
      "color": "#1C2D4E"
    },
    {
      "x": 7,
      "y": 0,
      "color": "#000000"
    },
    {
      "x": 0,
      "y": 1,
      "color": "#FF6F61"
    },
    {
      "x": 1,
      "y": 1,
      "color": "#FF9A85"
    },
    {
      "x": 2,
      "y": 1,
      "color": "#FCD8C4"
    },
    {
      "x": 3,
      "y": 1,
      "color": "#B3DDE8"
    },
    {
      "x": 4,
      "y": 1,
      "color": "#A3B2C8"
    },
    {
      "x": 5,
      "y": 1,
      "color": "#7B4A88"
    },
    {
      "x": 6,
      "y": 1,
      "color": "#2B252B"
    },
    {
      "x": 7,
      "y": 1,
      "color": "#000000"
    },
    {
      "x": 0,
      "y": 2,
      "color": "#FFC8A9"
    },
    {
      "x": 1,
      "y": 2,
      "color": "#F7B7A3"
    },
    {
      "x": 2,
      "y": 2,
      "color": "#E0E1E6"
    },
    {
      "x": 3,
      "y": 2,
      "color": "#D9DAD9"
    },
    {
      "x": 4,
      "y": 2,
      "color": "#C5C7C0"
    },
    {
      "x": 5,
      "y": 2,
      "color": "#A6B3C3"
    },
    {
      "x": 6,
      "y": 2,
      "color": "#6B7C97"
    },
    {
      "x": 7,
      "y": 2,
      "color": "#000000"
    },
    {
      "x": 0,
      "y": 3,
      "color": "#FF6F61"
    },
    {
      "x": 1,
      "y": 3,
      "color": "#E67E22"
    },
    {
      "x": 2,
      "y": 3,
      "color": "#F2D5C1"
    },
    {
      "x": 3,
      "y": 3,
      "color": "#C4DFFB"
    },
    {
      "x": 4,
      "y": 3,
      "color": "#B5D7E9"
    },
    {
      "x": 5,
      "y": 3,
      "color": "#8AA9C8"
    },
    {
      "x": 6,
      "y": 3,
      "color": "#355F7D"
    },
    {
      "x": 7,
      "y": 3,
      "color": "#000000"
    },
    {
      "x": 0,
      "y": 4,
      "color": "#FF8A5B"
    },
    {
      "x": 1,
      "y": 4,
      "color": "#FFB3A6"
    },
    {
      "x": 2,
      "y": 4,
      "color": "#E1B0B8"
    },
    {
      "x": 3,
      "y": 4,
      "color": "#C5C7C0"
    },
    {
      "x": 4,
      "y": 4,
      "color": "#B3E2FF"
    },
    {
      "x": 5,
      "y": 4,
      "color": "#9CB4E2"
    },
    {
      "x": 6,
      "y": 4,
      "color": "#3870A1"
    },
    {
      "x": 7,
      "y": 4,
      "color": "#000000"
    },
    {
      "x": 0,
      "y": 5,
      "color": "#F9C9D6"
    },
    {
      "x": 1,
      "y": 5,
      "color": "#C6B1C5"
    },
    {
      "x": 2,
      "y": 5,
      "color": "#A0B4C2"
    },
    {
      "x": 3,
      "y": 5,
      "color": "#B7A5BF"
    },
    {
      "x": 4,
      "y": 5,
      "color": "#8DABEA"
    },
    {
      "x": 5,
      "y": 5,
      "color": "#4C789D"
    },
    {
      "x": 6,
      "y": 5,
      "color": "#3B4B5A"
    },
    {
      "x": 7,
      "y": 5,
      "color": "#000000"
    },
    {
      "x": 0,
      "y": 6,
      "color": "#FDAB73"
    },
    {
      "x": 1,
      "y": 6,
      "color": "#F2D5C1"
    },
    {
      "x": 2,
      "y": 6,
      "color": "#D0E1E0"
    },
    {
      "x": 3,
      "y": 6,
      "color": "#A6B3C3"
    },
    {
      "x": 4,
      "y": 6,
      "color": "#9AA3B8"
    },
    {
      "x": 5,
      "y": 6,
      "color": "#7AB7E5"
    },
    {
      "x": 6,
      "y": 6,
      "color": "#2C4D76"
    },
    {
      "x": 7,
      "y": 6,
      "color": "#000000"
    },
    {
      "x": 0,
      "y": 7,
      "color": "#FF6F61"
    },
    {
      "x": 1,
      "y": 7,
      "color": "#FF8A5B"
    },
    {
      "x": 2,
      "y": 7,
      "color": "#FFFFFF"
    },
    {
      "x": 3,
      "y": 7,
      "color": "#C5C7C0"
    },
    {
      "x": 4,
      "y": 7,
      "color": "#B3DDE8"
    },
    {
      "x": 5,
      "y": 7,
      "color": "#A6C8E0"
    },
    {
      "x": 6,
      "y": 7,
      "color": "#000000"
    },
    {
      "x": 7,
      "y": 7,
      "color": "#000000"
    }
  ],
  "generationSpec": {
    "emotionPair": [
      "longing",
      "resolve"
    ],
    "emotionMoods": {
      "longing": [
        "stretched diagonal",
        "distant warmth",
        "unfinished approach"
      ],
      "resolve": [
        "clear boundary",
        "firm axis",
        "locked shape"
      ]
    },
    "layout": {
      "name": "argument_grid",
      "description": "Two patterns fight for control of the 8x8 canvas."
    },
    "flow": "cross_current",
    "patterns": {
      "longing": "flood",
      "resolve": "fault_line"
    },
    "edgeStyle": "receding_edges",
    "contrastType": "single_vs_many",
    "shapeSeed": "broken_line",
    "composition": {
      "name": "near_vs_far",
      "idea": "Close paired marks are separated from distant echoes by a wide quiet field."
    },
    "palette": {
      "name": "connection_alienation",
      "colors": [
        "warm_coral",
        "soft_amber",
        "cold_slate",
        "blue_black",
        "signal_cyan"
      ]
    },
    "referenceExample": {
      "title": "Wonder Through Rain",
      "emotionPair": [
        "melancholy",
        "wonder"
      ],
      "layout": "last_light",
      "flow": "drip",
      "pattern": "muted blue rain field interrupted by a small floating glow",
      "edge": "faded_border",
      "shape": "star",
      "palette": "melancholy_wonder"
    },
    "generationRules": [
      "Pick 1 emotional contrast.",
      "Pick 1 layout template.",
      "Pick 1 flow.",
      "Pick 1 pattern type for emotion A.",
      "Pick 1 pattern type for emotion B.",
      "Pick 1 edge style.",
      "Pick 1 contrast type.",
      "Pick 1 shape seed as the central object.",
      "Apply 1 to 6 broken pixels to create imperfection.",
      "Leave at least 10 percent negative space unless the mood is panic, rage, urgency, euphoria, or pressure.",
      "Use the shape seed as an abstract organizing metaphor, not as a literal icon.",
      "Make the two selected pattern types visibly collide, overlap, interrupt, or trade space.",
      "Prefer 4 to 8 distinct hex colors, with at least one quiet field color and one accent color.",
      "Keep the 8x8 grid readable at thumbnail size by preserving clear large-scale structure.",
      "Let one emotion dominate 55 to 70 percent of the square unless the selected layout demands balance.",
      "Use broken pixels as intentional disruptions, scars, repairs, leaks, or false echoes.",
      "Avoid perfectly even distribution unless the chosen composition is control, serenity, clarity, or certainty.",
      "Give the main collision a location: center, edge, corner, diagonal, border, or channel."
    ],
    "brokenPixels": 6,
    "negativeSpaceRule": "Leave at least 10 percent negative space unless the chosen emotional tone needs dense pressure."
  },
  "key": "e89229a668e1faf318cfcd2ced398ff526968b537bd0be7f02cd5f40c1b11896",
  "pixelHash": "e89229a668e1faf318cfcd2ced398ff526968b537bd0be7f02cd5f40c1b11896",
  "jsonFile": "e89229a668e1faf318cfcd2ced398ff526968b537bd0be7f02cd5f40c1b11896.json",
  "svgFile": "e89229a668e1faf318cfcd2ced398ff526968b537bd0be7f02cd5f40c1b11896.svg",
  "createdAt": "2026-06-04T04:01:56.336896+00:00"
}
